streamlit_jupyter/__init__.py
streamlit_jupyter/_modidx.py
streamlit_jupyter/core.py
streamlit_jupyter/utils.py
streamlit_jupyter-0.2.1.dist-info/LICENSE
streamlit_jupyter-0.2.1.dist-info/METADATA
streamlit_jupyter-0.2.1.dist-info/WHEEL
streamlit_jupyter-0.2.1.dist-info/entry_points.txt
streamlit_jupyter-0.2.1.dist-info/top_level.txt
streamlit_jupyter-0.2.1.dist-info/RECORD
