Metadata-Version: 2.1
Name: streamlit-jupyter
Version: 0.2.1
Summary: Simple Python package to preview and develop streamlit apps in jupyter notebooks
Home-page: https://github.com/ddobrinskiy/streamlit-jupyter
Author: David Dobrinskiy
Author-email: david@dobrinskiy.me
License: Apache Software License 2.0
Keywords: nbdev jupyter notebook python
Classifier: Development Status :: 4 - Beta
Classifier: Intended Audience :: Developers
Classifier: Natural Language :: English
Classifier: Programming Language :: Python :: 3.8
Classifier: Programming Language :: Python :: 3.9
Classifier: Programming Language :: Python :: 3.10
Classifier: Programming Language :: Python :: 3.11
Classifier: License :: OSI Approved :: Apache Software License
Requires-Python: >=3.8
Provides-Extra: dev
License-File: LICENSE
